[
  {"codigo":"00001",
    "1": ["a","b","a","a","c","a","b","a","a","c","a","b","a","a","c","a","b","a","a","c","a","b","a","a","c","a","b","a","a","c","a","b","a","a","c","a","b","a","a","c"],
    "2": ["a","b","a","a","c","a","b","a","a","c","a","b","a","a","c","a","b","a","a","c","a","b","a","a","c","a","b","a","a","c","a","b","a","a","c","a","b","a","a","c"],
    "3": ["a","b","a","a","c","a","b","a","a","c","a","b","a","a","c","a","b","a","a","c","a","b","a","a","c","a","b","a","a","c","a","b","a","a","c","a","b","a","a","c"]
  }
  ,{"codigo":"00002",
    "1": ["a","b","a","a","c","a","b","a","a","c","a","b","a","a","c","a","b","a","a","c","a","b","a","a","c","a","b","a","a","c","a","b","a","a","c","a","b","a","a","c"],
    "2": ["a","b","a","a","c","a","b","a","a","c","a","b","a","a","c","a","b","a","a","c","a","b","a","a","c","a","b","a","a","c","a","b","a","a","c","a","b","a","a","c"],
    "3": ["a","b","a","a","c","a","b","a","a","c","a","b","a","a","c","a","b","a","a","c","a","b","a","a","c","a","b","a","a","c","a","b","a","a","c","a","b","a","a","c"]
  }
]
